Chrmnder_lib/__init__.py
Chrmnder_lib/pokemon.csv
Chrmnder_lib/random_pokemon.py
Chrmnder_lib-1.0.1.dist-info/METADATA
Chrmnder_lib-1.0.1.dist-info/WHEEL
Chrmnder_lib-1.0.1.dist-info/top_level.txt
Chrmnder_lib-1.0.1.dist-info/RECORD
